cms_distributions
