Metadata-Version: 1.0
Name: cms-distributions
Version: 0.2
Summary: Gaussian distributions
Home-page: UNKNOWN
Author: Cornelius M
Author-email: jdialogc@gmail.com
License: UNKNOWN
Platform: UNKNOWN
